setup.py
Products/__init__.py
Products.ATBiblioStyles.egg-info/PKG-INFO
Products.ATBiblioStyles.egg-info/SOURCES.txt
Products.ATBiblioStyles.egg-info/dependency_links.txt
Products.ATBiblioStyles.egg-info/namespace_packages.txt
Products.ATBiblioStyles.egg-info/not-zip-safe
Products.ATBiblioStyles.egg-info/requires.txt
Products.ATBiblioStyles.egg-info/top_level.txt
Products/ATBiblioStyles/LICENSE.txt
Products/ATBiblioStyles/README.txt
Products/ATBiblioStyles/__init__.py
Products/ATBiblioStyles/bib_tool.gif
Products/ATBiblioStyles/config.py
Products/ATBiblioStyles/configure.zcml
Products/ATBiblioStyles/interface.py
Products/ATBiblioStyles/modulealiases.py
Products/ATBiblioStyles/profiles.zcml
Products/ATBiblioStyles/refresh.txt
Products/ATBiblioStyles/version.txt
Products/ATBiblioStyles/content/__init__.py
Products/ATBiblioStyles/content/customstyle.py
Products/ATBiblioStyles/content/customstylefolder.py
Products/ATBiblioStyles/content/customstyleset.py
Products/ATBiblioStyles/doc/Manual.txt
Products/ATBiblioStyles/doc/BibrefStyleExample/BibrefStyleExample.py
Products/ATBiblioStyles/doc/BibrefStyleExample/__init__.py
Products/ATBiblioStyles/exportimport/__init__.py
Products/ATBiblioStyles/exportimport/bibliostylestool.py
Products/ATBiblioStyles/exportimport/configure.zcml
Products/ATBiblioStyles/exportimport/setuphandlers.py
Products/ATBiblioStyles/i18n/atbibliostyles-en.po
Products/ATBiblioStyles/i18n/atbibliostyles-fr.po
Products/ATBiblioStyles/i18n/atbibliostyles-nl.po
Products/ATBiblioStyles/i18n/atbibliostyles.pot
Products/ATBiblioStyles/profiles/default/bibliostylestool.xml
Products/ATBiblioStyles/profiles/default/componentregistry.xml
Products/ATBiblioStyles/profiles/default/export_steps.xml
Products/ATBiblioStyles/profiles/default/factorytool.xml
Products/ATBiblioStyles/profiles/default/import_steps.xml
Products/ATBiblioStyles/profiles/default/metadata.xml
Products/ATBiblioStyles/profiles/default/propertiestool.xml
Products/ATBiblioStyles/profiles/default/skins.xml
Products/ATBiblioStyles/profiles/default/toolset.xml
Products/ATBiblioStyles/profiles/default/types.xml
Products/ATBiblioStyles/profiles/default/types/BibrefCustomStyle.xml
Products/ATBiblioStyles/profiles/default/types/BibrefCustomStyleFolder.xml
Products/ATBiblioStyles/profiles/default/types/BibrefCustomStyleSet.xml
