Metadata-Version: 1.0
Name: Products.ATBiblioStyles
Version: 1.0.0
Summary: Bibliography styles for CMFBibliographyAT
Home-page: http://pypi.python.org/pypi/Products.ATBiblioStyles
Author: Andreas Jung
Author-email: info@zopyx.com
License: LGPL 3
Keywords: CMFBibliographyAT
Platform: UNKNOWN
Classifier: Programming Language :: Python
Classifier: Framework :: Zope2
Classifier: Framework :: Plone
